<?xml version='1.0'?>
<!DOCTYPE webpage PUBLIC "-//Norman Walsh//DTD Website V2.4.1//EN"
                         "dtd/website.dtd">

<webpage id="screenshots" lang="en">

  <head>
    <title>Screenshots</title>
    <summary>What everyone is after...</summary>
  </head>

  <para>
    Here are a few screenshots of the development version. More should
    be added...
  </para>

  <para role="screenshot">
    <ulink url="screenshots/gimp-misc.png">
      <mediaobject>
        <imageobject>
          <imagedata fileref="screenshots/gimp-misc-thumb.png"/>
        </imageobject>
        <textobject>
          <phrase>Showing off some new stuff</phrase>
        </textobject>
      </mediaobject>
    </ulink>
    This desktop shows off some of the changes in GIMP 2.3.
  </para>

  <para role="screenshot">
    <ulink url="screenshots/gimp-prefs-color-management.png">
      <mediaobject>
        <imageobject>
          <imagedata fileref="screenshots/gimp-prefs-color-management-thumb.png"/>
        </imageobject>
        <textobject>
          <phrase>Configuration of color management</phrase>
        </textobject>
      </mediaobject>
    </ulink>
    The new Color Management section in the preferences. The image
    display does already respect these settings but there's still a
    lot to do to fully integate color management into GIMP.
  </para>

  <para role="screenshot">
    <ulink url="screenshots/gimp-help-browser.png">
      <mediaobject>
        <imageobject>
          <imagedata fileref="screenshots/gimp-help-browser-thumb.png"/>
        </imageobject>
        <textobject>
          <phrase>GIMP Help Browser</phrase>
        </textobject>
      </mediaobject>
    </ulink>
    The Help Browser plug-in has undergone some usability improvements.
  </para>

</webpage>
